CHANGELOG.rst
MANIFEST.in
README.rst
setup.py
versions.py
hg_versions.egg-info/PKG-INFO
hg_versions.egg-info/SOURCES.txt
hg_versions.egg-info/dependency_links.txt
hg_versions.egg-info/top_level.txt