Metadata-Version: 1.0
Name: hg-versions
Version: 0.4.1
Summary: display the version information for Mercurial and all installed extensions
Home-page: https://bitbucket.org/keimlink/hg-versions/src
Author: Markus Zapke-Gruendemann
Author-email: markus@keimlink.de
License: GNU GPLv2+
Platform: UNKNOWN
Classifier: Development Status :: 4 - Beta
Classifier: Environment :: Console
Classifier: Intended Audience :: Developers
Classifier: License :: OSI Approved :: GNU General Public License (GPL)
Classifier: Operating System :: OS Independent
Classifier: Programming Language :: Python
Classifier: Topic :: Software Development :: Version Control
